AUTHORS.rst
CONTRIBUTING.rst
HISTORY.rst
LICENSE
MANIFEST.in
README.rst
setup.cfg
setup.py
docs/Makefile
docs/authors.rst
docs/conf.py
docs/contributing.rst
docs/history.rst
docs/index.rst
docs/installation.rst
docs/make.bat
docs/readme.rst
docs/usage.rst
prueba_primo/__init__.py
prueba_primo/cli.py
prueba_primo/prueba_primo.py
prueba_primo.egg-info/PKG-INFO
prueba_primo.egg-info/SOURCES.txt
prueba_primo.egg-info/dependency_links.txt
prueba_primo.egg-info/entry_points.txt
prueba_primo.egg-info/not-zip-safe
prueba_primo.egg-info/requires.txt
prueba_primo.egg-info/top_level.txt
tests/test_prueba_primo.py