Metadata-Version: 1.1
Name: prueba-primo
Version: 0.2.0
Summary: Este es un codigo que comprueba numeros primos
Home-page: https://github.com/jorgestivenm/prueba_primo
Author: Jorge Steven Martinez Osorio
Author-email: jorgestivenm@gmail.com
License: MIT license
Keywords: prueba_primo
Platform: UNKNOWN
Classifier: Development Status :: 2 - Pre-Alpha
Classifier: Intended Audience :: Developers
Classifier: License :: OSI Approved :: MIT License
Classifier: Natural Language :: English
Classifier: Programming Language :: Python :: 2
Classifier: Programming Language :: Python :: 2.7
Classifier: Programming Language :: Python :: 3
Classifier: Programming Language :: Python :: 3.4
Classifier: Programming Language :: Python :: 3.5
Classifier: Programming Language :: Python :: 3.6
